table2sql/__init__.py
table2sql/cli.py
table2sql/converters/from_csv.py
table2sql/converters/from_excel.py
table2sql/helpers.py
table2sql/main.py
table2sql-1.0.5.dist-info/entry_points.txt
table2sql-1.0.5.dist-info/WHEEL
table2sql-1.0.5.dist-info/METADATA
table2sql-1.0.5.dist-info/RECORD
