Metadata-Version: 2.1
Name: table2sql
Version: 1.0.5
Summary: 
Home-page: https://github.com/piotrgredowski/table2sql
License: MIT
Author: Piotr Gredowski
Author-email: piotrgredowski@gmail.com
Requires-Python: >=3.6.2,<4.0
Classifier: License :: OSI Approved :: MIT License
Classifier: Programming Language :: Python :: 3
Classifier: Programming Language :: Python :: 3.7
Classifier: Programming Language :: Python :: 3.8
Classifier: Programming Language :: Python :: 3.9
Classifier: Programming Language :: Python :: 3.10
Classifier: Programming Language :: Python :: 3.10
Classifier: Programming Language :: Python :: 3.6
Classifier: Programming Language :: Python :: 3.7
Classifier: Programming Language :: Python :: 3.8
Classifier: Programming Language :: Python :: 3.9
Classifier: Topic :: Software Development :: Libraries :: Python Modules
Requires-Dist: click (>=8.0.1,<9.0.0)
Requires-Dist: openpyxl (>=3.0.7,<4.0.0)
Project-URL: Bug Tracker, https://github.com/piotrgredowski/table2sql/issues
